{"format":2,"version":"5.5","globals":"38c562db668a4c95c907bca7a3be0717","files":{"src_main_python___init___py":{"hash":"51509ae6427d630ccb16e20585159b5c","index":{"nums":[1,1,0,0,0,0,0],"html_filename":"src_main_python___init___py.html","relative_filename":"src/main/python/__init__.py"}},"src_main_python_actuator_py":{"hash":"1c08fa89a064d6089935af3fdc146cba","index":{"nums":[1,3,0,1,0,0,0],"html_filename":"src_main_python_actuator_py.html","relative_filename":"src/main/python/actuator.py"}},"src_main_python_hx711_py":{"hash":"977a418989835ea340ab08a48d84085c","index":{"nums":[1,77,0,21,0,0,0],"html_filename":"src_main_python_hx711_py.html","relative_filename":"src/main/python/hx711.py"}},"src_main_python_light_sensor_py":{"hash":"80682c79005339c7e91b57d78d504c7c","index":{"nums":[1,13,0,0,0,0,0],"html_filename":"src_main_python_light_sensor_py.html","relative_filename":"src/main/python/light_sensor.py"}},"src_main_python_machine_py":{"hash":"9002de9cd588cf732f833c67a6f70f44","index":{"nums":[1,232,0,1,0,0,0],"html_filename":"src_main_python_machine_py.html","relative_filename":"src/main/python/machine.py"}},"src_main_python_micropython_py":{"hash":"7d60a983a0d7a344d3e245deb7ff30a9","index":{"nums":[1,11,0,0,0,0,0],"html_filename":"src_main_python_micropython_py.html","relative_filename":"src/main/python/micropython.py"}},"src_main_python_motor_py":{"hash":"13e3542ed9e5b7ada0d0f343131ccdf3","index":{"nums":[1,17,0,0,0,0,0],"html_filename":"src_main_python_motor_py.html","relative_filename":"src/main/python/motor.py"}},"src_main_python_motor_bidirectional_py":{"hash":"8119e65af3abfbba0b8cd672726f2bb7","index":{"nums":[1,47,0,4,0,0,0],"html_filename":"src_main_python_motor_bidirectional_py.html","relative_filename":"src/main/python/motor_bidirectional.py"}},"src_main_python_scale_py":{"hash":"08cdaea7f668818658534788a71b4e52","index":{"nums":[1,21,0,0,0,0,0],"html_filename":"src_main_python_scale_py.html","relative_filename":"src/main/python/scale.py"}},"src_main_python_sensor_py":{"hash":"3baacea7a8076d3b270a02608132bcc6","index":{"nums":[1,24,0,2,0,0,0],"html_filename":"src_main_python_sensor_py.html","relative_filename":"src/main/python/sensor.py"}},"src_main_python_sensor_adc_py":{"hash":"5c3e6213f730249d9730c265e7c08ea9","index":{"nums":[1,9,0,0,0,0,0],"html_filename":"src_main_python_sensor_adc_py.html","relative_filename":"src/main/python/sensor_adc.py"}},"src_main_python_servo_py":{"hash":"65ab058773055616cd72dba5af75ea6c","index":{"nums":[1,20,0,0,0,0,0],"html_filename":"src_main_python_servo_py.html","relative_filename":"src/main/python/servo.py"}},"src_main_python_utime_py":{"hash":"8e0c75fdaa2b951599ae07408ca3117e","index":{"nums":[1,13,0,1,0,0,0],"html_filename":"src_main_python_utime_py.html","relative_filename":"src/main/python/utime.py"}},"src_main_python_valve_py":{"hash":"00569859b2c95bfb888b467f10fcf0f7","index":{"nums":[1,31,0,0,0,0,0],"html_filename":"src_main_python_valve_py.html","relative_filename":"src/main/python/valve.py"}},"src_main_python_water_sensor_py":{"hash":"4ed3cdea1064d5d04ddaf570de956dc4","index":{"nums":[1,11,0,0,0,0,0],"html_filename":"src_main_python_water_sensor_py.html","relative_filename":"src/main/python/water_sensor.py"}},"src_test_python___init___py":{"hash":"51509ae6427d630ccb16e20585159b5c","index":{"nums":[1,1,0,0,0,0,0],"html_filename":"src_test_python___init___py.html","relative_filename":"src/test/python/__init__.py"}},"src_test_python_test_light_sensor_py":{"hash":"4b1d02bb2ba01f9992cc22b7b0d2977d","index":{"nums":[1,22,0,1,0,0,0],"html_filename":"src_test_python_test_light_sensor_py.html","relative_filename":"src/test/python/test_light_sensor.py"}},"src_test_python_test_motor_py":{"hash":"dacbfbc64da1e72c35dd0260e3dea197","index":{"nums":[1,26,0,1,0,0,0],"html_filename":"src_test_python_test_motor_py.html","relative_filename":"src/test/python/test_motor.py"}},"src_test_python_test_motor_bidirectional_py":{"hash":"4da0f7f27e30db1de0ed4cde43be508b","index":{"nums":[1,55,0,1,0,0,0],"html_filename":"src_test_python_test_motor_bidirectional_py.html","relative_filename":"src/test/python/test_motor_bidirectional.py"}},"src_test_python_test_scale_py":{"hash":"38f758fed3f5e5b06439dc0ff7906a0c","index":{"nums":[1,29,0,1,0,0,0],"html_filename":"src_test_python_test_scale_py.html","relative_filename":"src/test/python/test_scale.py"}},"src_test_python_test_servo_py":{"hash":"73f8ab450cdf7af1428c1b0256c23499","index":{"nums":[1,21,0,1,0,0,0],"html_filename":"src_test_python_test_servo_py.html","relative_filename":"src/test/python/test_servo.py"}},"src_test_python_test_valve_py":{"hash":"f3bc7580bbf26a7b3ebe1d23e778d306","index":{"nums":[1,61,0,1,0,0,0],"html_filename":"src_test_python_test_valve_py.html","relative_filename":"src/test/python/test_valve.py"}},"src_test_python_test_water_sensor_py":{"hash":"60e79e974a3f97a0f6969676b69a17fb","index":{"nums":[1,23,0,1,0,0,0],"html_filename":"src_test_python_test_water_sensor_py.html","relative_filename":"src/test/python/test_water_sensor.py"}}}}